romaji/__init__.py
romaji/filter.py
romaji/mapping.py
romaji/substring.py
romaji/system.py
romaji/transliteration.py
romaji/transliterator.py
romaji-0.1.0.dist-info/LICENSE
romaji-0.1.0.dist-info/METADATA
romaji-0.1.0.dist-info/WHEEL
romaji-0.1.0.dist-info/top_level.txt
romaji-0.1.0.dist-info/RECORD
